DaPy/__init__.py
DaPy/conf.py
DaPy/io.py
DaPy/matlib.py
DaPy/operation.py
DaPy/core/DataSet.py
DaPy/core/__init__.py
DaPy/core/io.py
DaPy/core/sqlparser.py
DaPy/core/base/BaseSheet.py
DaPy/core/base/DapyObject.py
DaPy/core/base/IndexArray.py
DaPy/core/base/Matrix.py
DaPy/core/base/Row.py
DaPy/core/base/SafetyContainer.py
DaPy/core/base/Series.py
DaPy/core/base/Sheet.py
DaPy/core/base/__init__.py
DaPy/core/base/constant.py
DaPy/core/base/utils/__init__.py
DaPy/core/base/utils/py_string_transfer.py
DaPy/core/base/utils/utils_2to3.py
DaPy/core/base/utils/utils_grammar_parser.py
DaPy/core/base/utils/utils_isfunc.py
DaPy/core/base/utils/utils_join_table.py
DaPy/core/base/utils/utils_regression.py
DaPy/core/base/utils/utils_str_patterns.py
DaPy/core/base/utils/utils_toolkits.py
DaPy/datasets/__init__.py
DaPy/datasets/adult/adult.csv
DaPy/datasets/adult/data.csv
DaPy/datasets/example/data.csv
DaPy/datasets/example/sample.csv
DaPy/datasets/iris/data.csv
DaPy/datasets/iris/info.txt
DaPy/datasets/wine/data.csv
DaPy/datasets/wine/info.txt
DaPy/methods/__init__.py
DaPy/methods/evaluator.py
DaPy/methods/utils.py
DaPy/methods/classifiers/__init__.py
DaPy/methods/classifiers/classifier.py
DaPy/methods/classifiers/linear_models.py
DaPy/methods/classifiers/mlp.py
DaPy/methods/classifiers/tree.py
DaPy/methods/core/__init__.py
DaPy/methods/core/bp_model.py
DaPy/methods/core/linear_model.py
DaPy/methods/core/multilayer_perceptron.py
DaPy/methods/core/nlp_models.py
DaPy/methods/core/pagerank.py
DaPy/methods/core/tfidf.py
DaPy/methods/core/base/__init__.py
DaPy/methods/core/base/activators.py
DaPy/methods/core/base/layers.py
DaPy/methods/core/base/models.py
DaPy/methods/core/base/utils.py
DaPy/methods/nlp/LM.py
DaPy/methods/nlp/TFIDF.py
DaPy/methods/nlp/__init__.py
DaPy/methods/nlp/constant.py
DaPy/methods/nlp/ngram.py
DaPy/methods/nlp/utils.py
DaPy/methods/regressors/__init__.py
DaPy/methods/regressors/lr.py
DaPy/methods/statistic/__init__.py
DaPy/methods/statistic/compare_position.py
DaPy-1.16.1.dist-info/METADATA
DaPy-1.16.1.dist-info/WHEEL
DaPy-1.16.1.dist-info/top_level.txt
DaPy-1.16.1.dist-info/zip-safe
DaPy-1.16.1.dist-info/RECORD
