Metadata-Version: 2.1
Name: DaPy
Version: 1.16.1
Summary: Enjoy Your Tour in Data Mining
Home-page: http://dapy.kitgram.cn
Author: Xuansheng Wu
Author-email: wuxsmail@163.com
Maintainer: Xuansheng Wu
Maintainer-email: wuxsmail@163.com
License: GPL v3
Platform: all
Classifier: Development Status :: 4 - Beta
Classifier: Intended Audience :: Developers
Classifier: License :: OSI Approved :: GNU General Public License v3 (GPLv3)
Classifier: Programming Language :: Python :: 2
Classifier: Programming Language :: Python :: 3
Classifier: Intended Audience :: Developers
Classifier: Operating System :: OS Independent
Requires-Dist: xlrd (>=1.1.0)
Requires-Dist: xlwt (>=1.3.0)
